odoo/addons/web_group_by_percentage/README.rst
odoo/addons/web_group_by_percentage/__init__.py
odoo/addons/web_group_by_percentage/__manifest__.py
odoo/addons/web_group_by_percentage/i18n/ca.po
odoo/addons/web_group_by_percentage/i18n/es.po
odoo/addons/web_group_by_percentage/i18n/pt_BR.po
odoo/addons/web_group_by_percentage/i18n/web_group_by_percentage.pot
odoo/addons/web_group_by_percentage/i18n/zh_CN.po
odoo/addons/web_group_by_percentage/readme/CONTRIBUTORS.rst
odoo/addons/web_group_by_percentage/readme/DESCRIPTION.rst
odoo/addons/web_group_by_percentage/readme/USAGE.rst
odoo/addons/web_group_by_percentage/static/description/icon.png
odoo/addons/web_group_by_percentage/static/description/index.html
odoo/addons/web_group_by_percentage/static/description/screenshot.png
odoo/addons/web_group_by_percentage/static/src/js/backend.js
odoo/addons/web_group_by_percentage/static/src/scss/backend.scss
odoo/addons/web_group_by_percentage/templates/assets.xml
odoo12_addon_web_group_by_percentage-12.0.1.0.0.99.dev12.dist-info/METADATA
odoo12_addon_web_group_by_percentage-12.0.1.0.0.99.dev12.dist-info/WHEEL
odoo12_addon_web_group_by_percentage-12.0.1.0.0.99.dev12.dist-info/top_level.txt
odoo12_addon_web_group_by_percentage-12.0.1.0.0.99.dev12.dist-info/RECORD
